requestsdefaulter/__init__.py
requestsdefaulter-0.1.0.dist-info/METADATA
requestsdefaulter-0.1.0.dist-info/RECORD
requestsdefaulter-0.1.0.dist-info/WHEEL
requestsdefaulter-0.1.0.dist-info/top_level.txt
