Metadata-Version: 2.1
Name: requestsdefaulter
Version: 0.1.0
Summary: Small library to set default headers in requests
Home-page: https://github.com/ONSdigital/requestsdefaulter
Author: ONS
Author-email: UNKNOWN
License: MIT
Platform: UNKNOWN
